LICENSE
README.md
setup.py
dbcfg/__init__.py
dbcfg/dbcfgmain.py
dbcfg.egg-info/PKG-INFO
dbcfg.egg-info/SOURCES.txt
dbcfg.egg-info/dependency_links.txt
dbcfg.egg-info/entry_points.txt
dbcfg.egg-info/not-zip-safe
dbcfg.egg-info/top_level.txt
script/dbcfgtool.py