Metadata-Version: 2.1
Name: dbcfg
Version: 0.3.1
Summary: 数据库连接信息管理
Author: Chen chuan
Author-email: kcchen@139.com
Classifier: Programming Language :: Python :: 3
Classifier: License :: OSI Approved :: MIT License
Classifier: Operating System :: OS Independent
Requires-Python: >=3.7
License-File: LICENSE
